geoparquet_pydantic/__init__.py
geoparquet_pydantic/convert.py
geoparquet_pydantic/schemas.py
geoparquet_pydantic/validate.py
geoparquet_pydantic-0.0.1.dist-info/LICENSE
geoparquet_pydantic-0.0.1.dist-info/METADATA
geoparquet_pydantic-0.0.1.dist-info/WHEEL
geoparquet_pydantic-0.0.1.dist-info/top_level.txt
geoparquet_pydantic-0.0.1.dist-info/RECORD
