Metadata-Version: 2.1
Name: geoparquet_pydantic
Version: 0.0.1
Summary: Read/write geoparquet with the geojson-pydanic models.
License: MIT
Keywords: geoparquet,pydantic,geospatial
Classifier: Programming Language :: Python :: 3
Requires-Python: >=3.11
License-File: LICENSE
Requires-Dist: geojson-pydantic
Requires-Dist: pyarrow
Requires-Dist: shapely
Requires-Dist: pyproj
Requires-Dist: click
